pixelgreat_gui/__init__.py
pixelgreat_gui/core.py
pixelgreat_gui/settings.py
pixelgreat_gui/version.yml
pixelgreat_gui/widgets.py
pixelgreat_gui/windows.py
pixelgreat_gui/constants/__init__.py
pixelgreat_gui/constants/colors.py
pixelgreat_gui/constants/defaults.py
pixelgreat_gui/constants/enums.py
pixelgreat_gui/constants/links.py
pixelgreat_gui/constants/paths.py
pixelgreat_gui/constants/platform.py
pixelgreat_gui/constants/resources.py
pixelgreat_gui/constants/version.py
pixelgreat_gui/helpers/__init__.py
pixelgreat_gui/helpers/core.py
pixelgreat_gui/resources/icon.ico
pixelgreat_gui/resources/icon.png
pixelgreat_gui-1.1.3.dist-info/LICENSE
pixelgreat_gui-1.1.3.dist-info/METADATA
pixelgreat_gui-1.1.3.dist-info/WHEEL
pixelgreat_gui-1.1.3.dist-info/entry_points.txt
pixelgreat_gui-1.1.3.dist-info/top_level.txt
pixelgreat_gui-1.1.3.dist-info/RECORD
