Metadata-Version: 2.1
Name: pixelgreat-gui
Version: 1.1.3
Summary: A GUI for Pixelgreat: A highly realistic RGB pixel filter
Author-email: Ella Jameson <ellagjameson@gmail.com>
License: GNU GENERAL PUBLIC LICENSE
Project-URL: homepage, https://github.com/nimaid/pixelgreat-gui
Project-URL: repository, https://github.com/nimaid/pixelgreat-gui
Project-URL: Issues, https://github.com/nimaid/pixelgreat-gui/issues
Classifier: Topic :: Artistic Software
Classifier: Topic :: Multimedia :: Graphics
Classifier: Topic :: Multimedia :: Graphics :: Graphics Conversion
License-File: LICENSE
Requires-Dist: pyyaml
Requires-Dist: Pillow >10.0
Requires-Dist: pixelgreat
Requires-Dist: PyQt5
